acc_provision/__init__.py
acc_provision/acc_provision.py
acc_provision/apic_provision.py
acc_provision/flavors.yaml
acc_provision/test_main.py
acc_provision/versions.yaml
acc_provision/templates/__init__.py
acc_provision/templates/aci-cf-containers.yaml
acc_provision/templates/aci-containers.yaml
acc_provision/templates/provision-config.yaml
acc_provision-4.1.1.1.dist-info/DESCRIPTION.rst
acc_provision-4.1.1.1.dist-info/METADATA
acc_provision-4.1.1.1.dist-info/RECORD
acc_provision-4.1.1.1.dist-info/WHEEL
acc_provision-4.1.1.1.dist-info/entry_points.txt
acc_provision-4.1.1.1.dist-info/metadata.json
acc_provision-4.1.1.1.dist-info/top_level.txt
gitversion/__init__.py
gitversion/gitversion.py
