Metadata-Version: 2.0
Name: acc-provision
Version: 4.1.1.1
Summary: Tool to provision ACI for ACI Containers Controller  Build info: Release info not in the current build.
Home-page: http://github.com/noironetworks/acc-provision/
Author: Cisco Systems, Inc.
Author-email: apicapi@noironetworks.com
License: http://www.apache.org/licenses/LICENSE-2.0
Platform: UNKNOWN
Requires-Dist: jinja2
Requires-Dist: pyopenssl
Requires-Dist: pyyaml
Requires-Dist: requests
